Cipher/__init__.py
CipherModule-1.4.data/scripts/Cipher.py
CipherModule-1.4.dist-info/LICENSE
CipherModule-1.4.dist-info/METADATA
CipherModule-1.4.dist-info/WHEEL
CipherModule-1.4.dist-info/top_level.txt
CipherModule-1.4.dist-info/RECORD
