Metadata-Version: 2.1
Name: CipherModule
Version: 1.4
Summary: A python module to use ciphers easily
Home-page: https://github.com/Navid-d/Cipher
Author: Navid_d
Author-email: Navid.dargahi@gmail.com
License: UNKNOWN
Platform: UNKNOWN
Classifier: Programming Language :: Python :: 3
Classifier: License :: OSI Approved :: MIT License
Classifier: Operating System :: OS Independent
